djangocms_honeypot_captcha/__init__.py
djangocms_honeypot_captcha/cms_plugins.py
djangocms_honeypot_captcha/fields.py
djangocms_honeypot_captcha/widgets.py
djangocms_honeypot_captcha-1.0.0.0.dist-info/LICENSE
djangocms_honeypot_captcha-1.0.0.0.dist-info/METADATA
djangocms_honeypot_captcha-1.0.0.0.dist-info/WHEEL
djangocms_honeypot_captcha-1.0.0.0.dist-info/top_level.txt
djangocms_honeypot_captcha-1.0.0.0.dist-info/RECORD
