Metadata-Version: 2.1
Name: djangocms-honeypot-captcha
Version: 1.0.0.0
Summary: # Djangocms Honeypot Captcha
Requires-Dist: django-cms (>2)
Requires-Dist: aldryn-forms (>=2)
